MUX/muxtb.v
`timescale 1ns / 1ps
//////////////////////////////////////////////////////////////////////////////////
// Company: 
// Engineer: 
// 
// Create Date: 22.11.2024 21:31:14
// Design Name: 
// Module Name: muxtb
// Project Name: 
// Target Devices: 
// Tool Versions: 
// Description: 
// 
// Dependencies: 
// 
// Revision:
// Revision 0.01 - File Created
// Additional Comments:
// 
//////////////////////////////////////////////////////////////////////////////////


module mux(a,s,y);
    input [7:0]a;
    input [2:0] s;
    output reg y;
always@(*)
    begin
    case(s)
        3'b000:y=a[0];
        3'b001:y=a[1];
        3'b010:y=a[2];
        3'b011:y=a[3];
        3'b100:y=a[4];
        3'b101:y=a[5];
        3'b110:y=a[6];
        3'b111:y=a[7];
        default:$display("input value");
    endcase
end
endmodule

MUX/muxtbb.v
`timescale 1ns / 1ps
//////////////////////////////////////////////////////////////////////////////////
// Company: 
// Engineer: 
// 
// Create Date: 22.11.2024 21:32:56
// Design Name: 
// Module Name: muxtbb
// Project Name: 
// Target Devices: 
// Tool Versions: 
// Description: 
// 
// Dependencies: 
// 
// Revision:
// Revision 0.01 - File Created
// Additional Comments:
// 
//////////////////////////////////////////////////////////////////////////////////


module muxtbb();
    reg [2:0] s;
    reg [7:0] a;
    wire y;
    
    mux uut(.a(a), .s(s), .y(y));
    
    initial begin
        repeat (10) begin 
            a = $random;   // Assign a new random value to 'a'
            s = $random % 8; // Randomly select a value between 0-7
            #10; 
        end
        
        $finish;
    end
    
    initial begin
        $monitor("Time = %0t | a = %b | s = %b | y = %b", $time, a, s, y);
    end
endmodule

MUX/waveform.vcd
$date
   Fri Feb 14 00:31:08 2025
$end
$version
  2018.3
$end
$timescale
  1ps
$end
$scope module muxtbb $end
$var reg 3 ! s [2:0] $end
$var reg 8 " a [7:0] $end
$var wire 1 # y $end
$scope module uut $end
$var wire 8 $ a [7:0] $end
$var wire 3 % s [2:0] $end
$var reg 1 & y $end
$upscope $end
$upscope $end
$enddefinitions $end
#0
$dumpvars
b1 !
b100100 "
0#
b100100 $
b1 %
0&
$end
#10000
b11 !
b1001 "
1#
b1001 $
b11 %
1&
#20000
b101 !
b1101 "
0#
b1101 $
b101 %
0&
#30000
b10 !
b1100101 "
1#
b1100101 $
b10 %
1&
#40000
b101 !
b1 "
0#
b1 $
b101 %
0&
#50000
b101 !
b1110110 "
1#
b1110110 $
1&
#60000
b100 !
b11101101 "
0#
b11101101 $
b100 %
0&
#70000
b110 !
b11111001 "
1#
b11111001 $
b110 %
1&
#80000
b10 !
b11000101 "
b11000101 $
b10 %
1&
